[
    {
        "id": "eve-20260406-220325",
        "title": "白いシャツのイブ",
        "alt": "白いシャツと紺のリボンを身につけた銀髪の女性型アンドロイドのクローズアップ",
        "tags": [
            "イブ",
            "顔",
            "白シャツ"
        ],
        "category": [
            "poster"
        ],
        "featured": false
    },
    {
        "id": "eve-20260406-220325",
        "title": "白いシャツのイブ",
        "alt": "白いシャツと紺のリボンを身につけた銀髪の女性型アンドロイドのクローズアップ",
        "tags": [
            "イブ",
            "顔",
            "白シャツ"
        ],
        "category": [
            "poster"
        ],
        "featured": false
    },
    {
        "id": "eve-20260406-220325",
        "title": "白いシャツのイブ",
        "alt": "白いシャツと紺のリボンを身につけた銀髪の女性型アンドロイドのクローズアップ",
        "tags": [
            "イブ",
            "顔",
            "白シャツ"
        ],
        "category": [
            "poster"
        ],
        "featured": false
    }
]